mindbox/__init__.py
mindbox/_version.py
mindbox/client.py
mindbox/exceptions.py
mindbox/utils.py
mindbox/services/__init__.py
mindbox/services/base.py
mindbox/services/operations.py
mindbox/types/__init__.py
mindbox/types/operations.py
mindbox_sdk-1.0.3.dist-info/METADATA
mindbox_sdk-1.0.3.dist-info/WHEEL
mindbox_sdk-1.0.3.dist-info/top_level.txt
mindbox_sdk-1.0.3.dist-info/RECORD
