Metadata-Version: 2.1
Name: mindbox-sdk
Version: 1.0.3
Summary: Wrapper for working with Mindbox service API
Home-page: https://github.com/RTHeLL/mindbox-sdk
Download-URL: https://github.com/RTHeLL/mindbox-sdk/archive/master.zip
Author: Kinder (RTHeLL)
Author-email: k1ndermail@ya.ru
License: Apache License, Version 2.0, see LICENSE file
Keywords: wrapper,mindbox
Classifier: License :: OSI Approved :: Apache Software License
Classifier: Operating System :: OS Independent
Classifier: Environment :: Console
Classifier: Development Status :: 3 - Alpha
Classifier: Programming Language :: Python
Classifier: Programming Language :: Python :: 3
Classifier: Programming Language :: Python :: 3.8
Classifier: Programming Language :: Python :: 3.9
Classifier: Programming Language :: Python :: 3.10
Classifier: Programming Language :: Python :: 3.11
Classifier: Programming Language :: Python :: 3.12
Classifier: Programming Language :: Python :: 3 :: Only
Classifier: Programming Language :: Python :: Implementation :: PyPy
Requires-Dist: requests ~=2.27.1
Requires-Dist: pydantic ~=1.9.1
